permissible/__init__.py
permissible/filters.py
permissible/manage.py
permissible/permissions.py
permissible/policies.py
permissible/serializers.py
permissible/signals.py
permissible/views.py
permissible/admin/__init__.py
permissible/admin/default.py
permissible/admin/forms.py
permissible/admin/perm_domain.py
permissible/features/__init__.py
permissible/features/environment.py
permissible/features/steps/__init__.py
permissible/models/__init__.py
permissible/models/metaclasses.py
permissible/models/permissible_mixin.py
permissible/models/policy_lookup.py
permissible/models/role_based/base.py
permissible/models/role_based/core.py
permissible/models/role_based/hierarchical.py
permissible/models/utils/__init__.py
permissible/models/utils/assign.py
permissible/models/utils/clear.py
permissible/models/utils/reset.py
permissible/models/utils/update.py
permissible/perm_def/__init__.py
permissible/perm_def/base.py
permissible/perm_def/composite.py
permissible/perm_def/defaults.py
permissible/perm_def/model_resolver.py
permissible/perm_def/perm_def.py
permissible/perm_def/short_perms.py
permissible/templates/admin/permissible_changeform.html
permissible/templates/admin/user_permissible_changeform.html
permissible/templatetags/__init__.py
permissible/templatetags/custom_tags.py
permissible/utils/__init__.py
permissible/utils/signals.py
permissible/utils/views.py
permissible-0.7.9.dist-info/licenses/LICENSE
permissible-0.7.9.dist-info/METADATA
permissible-0.7.9.dist-info/WHEEL
permissible-0.7.9.dist-info/top_level.txt
permissible-0.7.9.dist-info/RECORD
