Metadata-Version: 2.4
Name: permissible
Version: 0.7.9
Summary: Extended, flexible and powerful object-level and rule-driven permissions for Django & Django REST framework
Project-URL: Homepage, https://github.com/gaussian/permissible
Project-URL: Issues, https://github.com/gaussian/permissible/issues
Requires-Python: >=3.12
License-File: LICENSE
Requires-Dist: Django<6,>=5
Requires-Dist: djangorestframework>=3
Provides-Extra: guardian
Requires-Dist: django-guardian==3.1.2; extra == "guardian"
Requires-Dist: djangorestframework-guardian; extra == "guardian"
Dynamic: license-file
